CHANGELOG.md
LICENSE
README.md
totype/__init__.py
totype/annotation_types.py
totype/exceptions.py
totype/fields.py
totype/func.py
totype/transform.py
totype-0.1.0.dist-info/LICENSE
totype-0.1.0.dist-info/WHEEL
totype-0.1.0.dist-info/METADATA
totype-0.1.0.dist-info/RECORD
