Metadata-Version: 2.1
Name: totype
Version: 0.1.0
Summary: Data converter
Home-page: https://github.com/pavelmaksimov/totype
License: Apache-2.0
Keywords: python,data-converter,data-transform
Author: Pavel Maksimov
Author-email: vur21@ya.ru
Requires-Python: >=3.8,<4.0
Classifier: License :: OSI Approved :: Apache Software License
Classifier: Programming Language :: Python :: 3
Classifier: Programming Language :: Python :: 3.10
Classifier: Programming Language :: Python :: 3.8
Classifier: Programming Language :: Python :: 3.9
Requires-Dist: dateutils
Requires-Dist: orjson
Requires-Dist: pendulum
Requires-Dist: simplejson
Requires-Dist: ujson
Project-URL: Repository, https://github.com/pavelmaksimov/totype.git
